roicat/ROInet.py
roicat/__init__.py
roicat/__main__.py
roicat/data_importing.py
roicat/helpers.py
roicat/pipelines.py
roicat/util.py
roicat/visualization.py
roicat/classification/__init__.py
roicat/classification/classifier.py
roicat/model_training/__init__.py
roicat/model_training/augmentation.py
roicat/model_training/model.py
roicat/model_training/simclr_training_helpers.py
roicat/model_training/train_simclr.py
roicat/model_training/train_simclr_PCA.py
roicat/tracking/__init__.py
roicat/tracking/alignment.py
roicat/tracking/blurring.py
roicat/tracking/clustering.py
roicat/tracking/scatteringWaveletTransformer.py
roicat/tracking/similarity_graph.py
roicat-1.5.5.dist-info/licenses/LICENSE.md
roicat-1.5.5.dist-info/METADATA
roicat-1.5.5.dist-info/WHEEL
roicat-1.5.5.dist-info/entry_points.txt
roicat-1.5.5.dist-info/top_level.txt
roicat-1.5.5.dist-info/RECORD
