Metadata-Version: 2.4
Name: roicat
Version: 1.5.5
Summary: A library for classifying and tracking ROIs.
Home-page: https://github.com/RichieHakim/ROICaT
Author: Richard Hakim
License: LICENSE
Keywords: neuroscience,neuroimaging,machine learning,deep learning
Requires-Python: >=3.10, <3.14
License-File: LICENSE.md
Provides-Extra: all
Requires-Dist: hdbscan==0.8.40; extra == "all"
Requires-Dist: holoviews[recommended]==1.21.0; extra == "all"
Requires-Dist: jupyter==1.0.0; extra == "all"
Requires-Dist: kymatio==0.3.0; extra == "all"
Requires-Dist: matplotlib==3.10.5; extra == "all"
Requires-Dist: natsort==8.4.0; extra == "all"
Requires-Dist: numpy==2.2.6; extra == "all"
Requires-Dist: opencv_contrib_python_headless<=4.12.0.88; extra == "all"
Requires-Dist: optuna==4.3.0; extra == "all"
Requires-Dist: Pillow==11.3.0; extra == "all"
Requires-Dist: pytest==8.4.1; extra == "all"
Requires-Dist: scikit_learn==1.7.1; extra == "all"
Requires-Dist: scipy==1.15.3; extra == "all"
Requires-Dist: seaborn==0.13.2; extra == "all"
Requires-Dist: sparse==0.17.0; extra == "all"
Requires-Dist: tqdm==4.67.1; extra == "all"
Requires-Dist: umap_learn==0.5.9.post2; extra == "all"
Requires-Dist: xxhash==3.5.0; extra == "all"
Requires-Dist: bokeh==3.7.3; extra == "all"
Requires-Dist: psutil==7.0.0; extra == "all"
Requires-Dist: py_cpuinfo==9.0.0; extra == "all"
Requires-Dist: PyYAML==6.0.2; extra == "all"
Requires-Dist: mat73==0.65; extra == "all"
Requires-Dist: torch==2.7.1; extra == "all"
Requires-Dist: torchvision==0.22.1; extra == "all"
Requires-Dist: torchaudio==2.7.1; extra == "all"
Requires-Dist: selenium==4.34.2; extra == "all"
Requires-Dist: skl2onnx==1.19.1; extra == "all"
Requires-Dist: onnx==1.17.0; extra == "all"
Requires-Dist: onnxruntime==1.22.1; extra == "all"
Requires-Dist: jupyter_bokeh==4.0.5; extra == "all"
Requires-Dist: onnx2torch==1.5.15; extra == "all"
Requires-Dist: scikit-image==0.25.2; extra == "all"
Requires-Dist: richfile>=0.4.5; extra == "all"
Requires-Dist: romatch-roicat>=0.1.1; extra == "all"
Requires-Dist: kornia==0.8.1; extra == "all"
Provides-Extra: all-latest
Requires-Dist: hdbscan; extra == "all-latest"
Requires-Dist: holoviews[recommended]; extra == "all-latest"
Requires-Dist: jupyter; extra == "all-latest"
Requires-Dist: kymatio; extra == "all-latest"
Requires-Dist: matplotlib; extra == "all-latest"
Requires-Dist: natsort; extra == "all-latest"
Requires-Dist: numpy; extra == "all-latest"
Requires-Dist: opencv_contrib_python_headless; extra == "all-latest"
Requires-Dist: optuna; extra == "all-latest"
Requires-Dist: Pillow; extra == "all-latest"
Requires-Dist: pytest; extra == "all-latest"
Requires-Dist: scikit_learn; extra == "all-latest"
Requires-Dist: scipy; extra == "all-latest"
Requires-Dist: seaborn; extra == "all-latest"
Requires-Dist: sparse; extra == "all-latest"
Requires-Dist: tqdm; extra == "all-latest"
Requires-Dist: umap_learn; extra == "all-latest"
Requires-Dist: xxhash; extra == "all-latest"
Requires-Dist: bokeh; extra == "all-latest"
Requires-Dist: psutil; extra == "all-latest"
Requires-Dist: py_cpuinfo; extra == "all-latest"
Requires-Dist: PyYAML; extra == "all-latest"
Requires-Dist: mat73; extra == "all-latest"
Requires-Dist: torch; extra == "all-latest"
Requires-Dist: torchvision; extra == "all-latest"
Requires-Dist: torchaudio; extra == "all-latest"
Requires-Dist: selenium; extra == "all-latest"
Requires-Dist: skl2onnx; extra == "all-latest"
Requires-Dist: onnx; extra == "all-latest"
Requires-Dist: onnxruntime; extra == "all-latest"
Requires-Dist: jupyter_bokeh; extra == "all-latest"
Requires-Dist: onnx2torch; extra == "all-latest"
Requires-Dist: scikit-image; extra == "all-latest"
Requires-Dist: richfile; extra == "all-latest"
Requires-Dist: romatch-roicat; extra == "all-latest"
Requires-Dist: kornia; extra == "all-latest"
Provides-Extra: core
Requires-Dist: jupyter==1.0.0; extra == "core"
Requires-Dist: matplotlib==3.10.5; extra == "core"
Requires-Dist: mat73==0.65; extra == "core"
Requires-Dist: natsort==8.4.0; extra == "core"
Requires-Dist: numpy==2.2.6; extra == "core"
Requires-Dist: optuna==4.3.0; extra == "core"
Requires-Dist: Pillow==11.3.0; extra == "core"
Requires-Dist: pytest==8.4.1; extra == "core"
Requires-Dist: PyYAML==6.0.2; extra == "core"
Requires-Dist: scikit_learn==1.7.1; extra == "core"
Requires-Dist: scipy==1.15.3; extra == "core"
Requires-Dist: seaborn==0.13.2; extra == "core"
Requires-Dist: sparse==0.17.0; extra == "core"
Requires-Dist: tqdm==4.67.1; extra == "core"
Requires-Dist: xxhash==3.5.0; extra == "core"
Requires-Dist: torch==2.7.1; extra == "core"
Requires-Dist: torchvision==0.22.1; extra == "core"
Requires-Dist: torchaudio==2.7.1; extra == "core"
Requires-Dist: psutil==7.0.0; extra == "core"
Requires-Dist: py_cpuinfo==9.0.0; extra == "core"
Requires-Dist: skl2onnx==1.19.1; extra == "core"
Requires-Dist: onnx==1.17.0; extra == "core"
Requires-Dist: onnxruntime==1.22.1; extra == "core"
Requires-Dist: richfile>=0.4.5; extra == "core"
Provides-Extra: classification
Requires-Dist: umap_learn==0.5.9.post2; extra == "classification"
Requires-Dist: bokeh==3.7.3; extra == "classification"
Requires-Dist: holoviews[recommended]==1.21.0; extra == "classification"
Requires-Dist: jupyter_bokeh==4.0.5; extra == "classification"
Requires-Dist: jupyter==1.0.0; extra == "classification"
Requires-Dist: matplotlib==3.10.5; extra == "classification"
Requires-Dist: mat73==0.65; extra == "classification"
Requires-Dist: natsort==8.4.0; extra == "classification"
Requires-Dist: numpy==2.2.6; extra == "classification"
Requires-Dist: optuna==4.3.0; extra == "classification"
Requires-Dist: Pillow==11.3.0; extra == "classification"
Requires-Dist: pytest==8.4.1; extra == "classification"
Requires-Dist: PyYAML==6.0.2; extra == "classification"
Requires-Dist: scikit_learn==1.7.1; extra == "classification"
Requires-Dist: scipy==1.15.3; extra == "classification"
Requires-Dist: seaborn==0.13.2; extra == "classification"
Requires-Dist: sparse==0.17.0; extra == "classification"
Requires-Dist: tqdm==4.67.1; extra == "classification"
Requires-Dist: xxhash==3.5.0; extra == "classification"
Requires-Dist: torch==2.7.1; extra == "classification"
Requires-Dist: torchvision==0.22.1; extra == "classification"
Requires-Dist: torchaudio==2.7.1; extra == "classification"
Requires-Dist: psutil==7.0.0; extra == "classification"
Requires-Dist: py_cpuinfo==9.0.0; extra == "classification"
Requires-Dist: skl2onnx==1.19.1; extra == "classification"
Requires-Dist: onnx==1.17.0; extra == "classification"
Requires-Dist: onnxruntime==1.22.1; extra == "classification"
Requires-Dist: richfile>=0.4.5; extra == "classification"
Provides-Extra: tracking
Requires-Dist: opencv_contrib_python_headless<=4.12.0.88; extra == "tracking"
Requires-Dist: hdbscan==0.8.40; extra == "tracking"
Requires-Dist: kymatio==0.3.0; extra == "tracking"
Requires-Dist: kornia==0.8.1; extra == "tracking"
Requires-Dist: romatch-roicat>=0.1.1; extra == "tracking"
Requires-Dist: jupyter==1.0.0; extra == "tracking"
Requires-Dist: matplotlib==3.10.5; extra == "tracking"
Requires-Dist: mat73==0.65; extra == "tracking"
Requires-Dist: natsort==8.4.0; extra == "tracking"
Requires-Dist: numpy==2.2.6; extra == "tracking"
Requires-Dist: optuna==4.3.0; extra == "tracking"
Requires-Dist: Pillow==11.3.0; extra == "tracking"
Requires-Dist: pytest==8.4.1; extra == "tracking"
Requires-Dist: PyYAML==6.0.2; extra == "tracking"
Requires-Dist: scikit_learn==1.7.1; extra == "tracking"
Requires-Dist: scipy==1.15.3; extra == "tracking"
Requires-Dist: seaborn==0.13.2; extra == "tracking"
Requires-Dist: sparse==0.17.0; extra == "tracking"
Requires-Dist: tqdm==4.67.1; extra == "tracking"
Requires-Dist: xxhash==3.5.0; extra == "tracking"
Requires-Dist: torch==2.7.1; extra == "tracking"
Requires-Dist: torchvision==0.22.1; extra == "tracking"
Requires-Dist: torchaudio==2.7.1; extra == "tracking"
Requires-Dist: psutil==7.0.0; extra == "tracking"
Requires-Dist: py_cpuinfo==9.0.0; extra == "tracking"
Requires-Dist: skl2onnx==1.19.1; extra == "tracking"
Requires-Dist: onnx==1.17.0; extra == "tracking"
Requires-Dist: onnxruntime==1.22.1; extra == "tracking"
Requires-Dist: richfile>=0.4.5; extra == "tracking"
Dynamic: author
Dynamic: description
Dynamic: description-content-type
Dynamic: home-page
Dynamic: keywords
Dynamic: license
Dynamic: license-file
Dynamic: provides-extra
Dynamic: requires-python
Dynamic: summary
